MANIFEST.in
setup.py
masonite_notifications.egg-info/PKG-INFO
masonite_notifications.egg-info/SOURCES.txt
masonite_notifications.egg-info/dependency_links.txt
masonite_notifications.egg-info/top_level.txt
notifications/Notifiable.py
notifications/Notify.py
notifications/__init__.py
notifications/exceptions.py
notifications/commands/NotificationCommand.py
notifications/commands/__init__.py
notifications/components/MailComponent.py
notifications/components/SlackComponent.py
notifications/components/__init__.py
notifications/providers/NotificationProvider.py
notifications/providers/__init__.py
notifications/snippets/mail/action.html
notifications/snippets/mail/heading.html
notifications/snippets/mail/line.html
notifications/snippets/mail/panel.html