Metadata-Version: 1.0
Name: masonite-notifications
Version: 1.0.0
Summary: The core for the Masonite framework
Home-page: https://github.com/MasoniteFramework/notifications
Author: Joseph Mancuso
Author-email: idmann509@gmail.com
License: UNKNOWN
Keywords: python web framework,python3,masonite
Platform: UNKNOWN
